tu_ruc_python_client/__init__.py
tu_ruc_python_client/client.py
tu_ruc_python_client/constants.py
tu_ruc_python_client/exceptions.py
tu_ruc_python_client/validations.py
tu_ruc_python_client-0.0.3.dist-info/LICENSE
tu_ruc_python_client-0.0.3.dist-info/METADATA
tu_ruc_python_client-0.0.3.dist-info/WHEEL
tu_ruc_python_client-0.0.3.dist-info/top_level.txt
tu_ruc_python_client-0.0.3.dist-info/RECORD
