Metadata-Version: 2.1
Name: tu_ruc_python_client
Version: 0.0.3
Summary: Cliente Python para la API de TURUC Paraguay 
Author-email: Sebastian Alvarez <ca.sebastianlv@gmail.com>, Esteban Fernandez <estebangfernandeza@gmail.com>
Project-URL: Homepage, https://github.com/ithdev/tu-ruc-python-client
Project-URL: Issues, https://github.com/ithdev/tu-ruc-python-client/issues
Classifier: Programming Language :: Python :: 3
Classifier: License :: OSI Approved :: MIT License
Classifier: Operating System :: OS Independent
Requires-Python: >=3.8
License-File: LICENSE
